<annotation>
	<folder>曾小龙</folder>
	<filename>192.168.10.113_01_20211206105547992_TIMING.jpg</filename>
	<path>E:\other_space\ai标识\曾小龙\曾小龙\192.168.10.113_01_20211206105547992_TIMING.jpg</path>
	<source>
		<database>Unknown</database>
	</source>
	<size>
		<width>1920</width>
		<height>1080</height>
		<depth>3</depth>
	</size>
	<segmented>0</segmented>
	<object>
		<name>platformTruck</name>
		<pose>Unspecified</pose>
		<truncated>0</truncated>
		<difficult>0</difficult>
		<bndbox>
			<xmin>940</xmin>
			<ymin>51</ymin>
			<xmax>1085</xmax>
			<ymax>263</ymax>
		</bndbox>
	</object>
	<object>
		<name>cementTruck</name>
		<pose>Unspecified</pose>
		<truncated>0</truncated>
		<difficult>0</difficult>
		<bndbox>
			<xmin>1282</xmin>
			<ymin>89</ymin>
			<xmax>1740</xmax>
			<ymax>499</ymax>
		</bndbox>
	</object>
	<object>
		<name>car</name>
		<pose>Unspecified</pose>
		<truncated>0</truncated>
		<difficult>0</difficult>
		<bndbox>
			<xmin>1731</xmin>
			<ymin>312</ymin>
			<xmax>1811</xmax>
			<ymax>427</ymax>
		</bndbox>
	</object>
	<object>
		<name>tyre</name>
		<pose>Unspecified</pose>
		<truncated>0</truncated>
		<difficult>0</difficult>
		<bndbox>
			<xmin>1499</xmin>
			<ymin>385</ymin>
			<xmax>1544</xmax>
			<ymax>464</ymax>
		</bndbox>
	</object>
	<object>
		<name>tyre</name>
		<pose>Unspecified</pose>
		<truncated>0</truncated>
		<difficult>0</difficult>
		<bndbox>
			<xmin>1430</xmin>
			<ymin>344</ymin>
			<xmax>1468</xmax>
			<ymax>424</ymax>
		</bndbox>
	</object>
	<object>
		<name>tyre</name>
		<pose>Unspecified</pose>
		<truncated>0</truncated>
		<difficult>0</difficult>
		<bndbox>
			<xmin>1326</xmin>
			<ymin>297</ymin>
			<xmax>1361</xmax>
			<ymax>364</ymax>
		</bndbox>
	</object>
	<object>
		<name>tyre</name>
		<pose>Unspecified</pose>
		<truncated>0</truncated>
		<difficult>0</difficult>
		<bndbox>
			<xmin>1292</xmin>
			<ymin>282</ymin>
			<xmax>1318</xmax>
			<ymax>345</ymax>
		</bndbox>
	</object>
</annotation>
